LICENSE
MANIFEST.in
README.md
pavement.py
setup.py
cashflows/__init__.py
cashflows/analysis.py
cashflows/bond.py
cashflows/common.py
cashflows/currency.py
cashflows/depreciation.py
cashflows/gtimeseries.py
cashflows/inflation.py
cashflows/loan.py
cashflows/prjflow.py
cashflows/rate.py
cashflows/savings.py
cashflows/taxing.py
cashflows/timeseries.py
cashflows/tvmm.py
cashflows/utilityfun.py
cashflows.egg-info/PKG-INFO
cashflows.egg-info/SOURCES.txt
cashflows.egg-info/dependency_links.txt
cashflows.egg-info/not-zip-safe
cashflows.egg-info/top_level.txt